xcu/__init__.py
xcu/main.py
xcu-1.0.2.dist-info/licenses/LICENSE
xcu-1.0.2.dist-info/METADATA
xcu-1.0.2.dist-info/WHEEL
xcu-1.0.2.dist-info/entry_points.txt
xcu-1.0.2.dist-info/top_level.txt
xcu-1.0.2.dist-info/RECORD
