Metadata-Version: 2.4
Name: xcu
Version: 1.0.2
Summary: Librería para facilitar la instalación de paquetes de python en Cuba sin gastar megas
Author-email: KeimaSenpai <KeimaSenpai@proton.me>
License: MIT License
Project-URL: Homepage, https://github.com/KeimaSenpai
Project-URL: Documentation, https://github.com/KeimaSenpai
Project-URL: Source, https://github.com/KeimaSenpai
Project-URL: Issues, https://github.com/KeimaSenpai
Project-URL: Community, https://t.me/KeimaSenpai
Keywords: Cuba,pip,packages
License-File: LICENSE
Dynamic: license-file
